lolapi
