Metadata-Version: 1.0
Name: lolapi
Version: 0.9.6
Summary: a Python wrapper for League of Legends RESTful API by Riot Games
Home-page: https://github.com/smotes/lolapi
Author: Steven Motes
Author-email: steven.motes@gmail.com
License: MIT
Platform: UNKNOWN
